MANIFEST.in
README.md
build.py
requirements-dev.txt
requirements.txt
setup.py
auto_file_flow.egg-info/PKG-INFO
auto_file_flow.egg-info/SOURCES.txt
auto_file_flow.egg-info/dependency_links.txt
auto_file_flow.egg-info/requires.txt
auto_file_flow.egg-info/top_level.txt
file_flow/__init__.py
file_flow/events.py
file_flow/handler.py
file_flow/io.py
file_flow/operation.py
file_flow/pipeline.py
file_flow/process.py
file_flow/watcher.py