Metadata-Version: 2.1
Name: auto-file-flow
Version: 0.0.1
Summary: An event system for file operations to execute commands for file events.
Home-page: https://github.com/Shahaf-F-S/file-flow
Author: Shahaf Frank-Shapir
Author-email: shahaffrs@gmail.com
License: MIT
Classifier: Intended Audience :: Developers
Classifier: License :: OSI Approved :: MIT License
Classifier: Programming Language :: Python
Classifier: Programming Language :: Python :: 3
Classifier: Programming Language :: Python :: 3.10
Classifier: Programming Language :: Python :: 3.11
Classifier: Operating System :: OS Independent
Provides-Extra: dev
